classification_models/__init__.py
classification_models/__version__.py
classification_models/utils.py
classification_models/weights.py
classification_models/common/__init__.py
classification_models/common/blocks.py
classification_models/keras_applications/__init__.py
classification_models/keras_applications/keras_applications/__init__.py
classification_models/keras_applications/keras_applications/setup.py
classification_models/keras_applications/keras_applications/keras_applications/__init__.py
classification_models/keras_applications/keras_applications/keras_applications/densenet.py
classification_models/keras_applications/keras_applications/keras_applications/imagenet_utils.py
classification_models/keras_applications/keras_applications/keras_applications/inception_resnet_v2.py
classification_models/keras_applications/keras_applications/keras_applications/inception_v3.py
classification_models/keras_applications/keras_applications/keras_applications/mobilenet.py
classification_models/keras_applications/keras_applications/keras_applications/mobilenet_v2.py
classification_models/keras_applications/keras_applications/keras_applications/nasnet.py
classification_models/keras_applications/keras_applications/keras_applications/resnet.py
classification_models/keras_applications/keras_applications/keras_applications/resnet50.py
classification_models/keras_applications/keras_applications/keras_applications/resnet_common.py
classification_models/keras_applications/keras_applications/keras_applications/resnet_v2.py
classification_models/keras_applications/keras_applications/keras_applications/resnext.py
classification_models/keras_applications/keras_applications/keras_applications/vgg16.py
classification_models/keras_applications/keras_applications/keras_applications/vgg19.py
classification_models/keras_applications/keras_applications/keras_applications/xception.py
classification_models/resnet/__init__.py
classification_models/resnet/blocks.py
image_classifiers-0.2.2.dist-info/METADATA
image_classifiers-0.2.2.dist-info/RECORD
image_classifiers-0.2.2.dist-info/WHEEL
image_classifiers-0.2.2.dist-info/top_level.txt
