Metadata-Version: 2.1
Name: image-classifiers
Version: 0.2.2
Summary: Image classification models. Keras.
Home-page: https://github.com/qubvel/classification_models
Author: Pavel Yakubovskiy
Author-email: qubvel@gmail.com
License: MIT
Platform: UNKNOWN
Classifier: License :: OSI Approved :: MIT License
Classifier: Programming Language :: Python
Classifier: Programming Language :: Python :: 3
Classifier: Programming Language :: Python :: Implementation :: CPython
Classifier: Programming Language :: Python :: Implementation :: PyPy
Requires-Python: >=3.0.0
Provides-Extra: tests
Requires-Dist: keras (>=2.1.0)
Provides-Extra: tests
Requires-Dist: scikit-image; extra == 'tests'
Requires-Dist: pytest; extra == 'tests'
